iotasecret
