Metadata-Version: 2.1
Name: iotasecret
Version: 0.0.0.6
Summary: Send secrets using iota.
Home-page: https://github.com/Tsangares/iotasecret
Author-email: william.wyatt@cgu.edu
License: UNKNOWN
Platform: UNKNOWN
Classifier: Programming Language :: Python :: 3
Classifier: License :: OSI Approved :: MIT License
Classifier: Operating System :: OS Independent
Requires-Python: >=3.7
